README.txt
pydicia.py
setup.cfg
setup.py
PyDicia.egg-info/PKG-INFO
PyDicia.egg-info/SOURCES.txt
PyDicia.egg-info/dependency_links.txt
PyDicia.egg-info/requires.txt
PyDicia.egg-info/top_level.txt
ez_setup/README.txt
ez_setup/__init__.py