Metadata-Version: 1.0
Name: PyDicia
Version: 0.1a3
Summary: Print labels, envelopes, US postage, and more using the endicia.com API
Home-page: http://cheeseshop.python.org/pypi/PyDicia
Author: Phillip J. Eby
Author-email: peak@eby-sarna.com
License: PSF or ZPL
Platform: UNKNOWN
